keda_dispatcher/__init__.py
keda_dispatcher/api/__init__.py
keda_dispatcher/api/proc.py
keda_dispatcher/app_factory.py
keda_dispatcher/deps.py
keda_dispatcher/logconf.py
keda_dispatcher/schemas.py
keda_dispatcher/server.py
keda_dispatcher/services/__init__.py
keda_dispatcher/services/proc.py
keda_dispatcher/services/queue.py
keda_dispatcher/settings.py
keda_dispatcher-0.1.3.dist-info/LICENSE
keda_dispatcher-0.1.3.dist-info/METADATA
keda_dispatcher-0.1.3.dist-info/WHEEL
keda_dispatcher-0.1.3.dist-info/entry_points.txt
keda_dispatcher-0.1.3.dist-info/RECORD
