Metadata-Version: 2.1
Name: keda-dispatcher
Version: 0.1.3
Summary: 
Author: Kevin-Tofu
Author-email: koheitech001@gmail.com
Requires-Python: >=3.10,<3.14
Classifier: Programming Language :: Python :: 3
Classifier: Programming Language :: Python :: 3.10
Classifier: Programming Language :: Python :: 3.11
Classifier: Programming Language :: Python :: 3.12
Requires-Dist: boto3 (>=1.42.11,<2.0.0)
Requires-Dist: fastapi (>=0.124.4,<0.125.0)
Requires-Dist: pydantic (>=2.12.5,<3.0.0)
Requires-Dist: python-multipart (>=0.0.21,<0.0.22)
Requires-Dist: redis (>=7.1.0,<8.0.0)
Requires-Dist: uvicorn[standard] (>=0.38.0,<0.39.0)
